sidh_optimizer/__init__.py
sidh_optimizer/formulas.py
sidh_optimizer/key_exchange.py
sidh_optimizer/paths.py
sidh_optimizer-0.1.0a2.dist-info/DESCRIPTION.rst
sidh_optimizer-0.1.0a2.dist-info/METADATA
sidh_optimizer-0.1.0a2.dist-info/RECORD
sidh_optimizer-0.1.0a2.dist-info/WHEEL
sidh_optimizer-0.1.0a2.dist-info/metadata.json
sidh_optimizer-0.1.0a2.dist-info/top_level.txt
